{
	"swagger": "2.0",
	"info": {
		"title": "negrodom API",
		"description": "This is an negrodomAPI, which is part of the English Language API Recipe Book.",
		"termsOfService": "http://apievangelist.com/terms-of-service.html",
		"version": "v1"
	},
	"host": "n.example.com",
	"basePath": "/",
	"schemes": ["http"],
	"produces": ["application/json"],
	"paths": {
		"/negrodom/": {
			"get": {
				"summary": "negrodom item",
				"description": "returns an negrodom item",
				"operationId": "getnegrodom",
				"parameters": [{
					"name": "q",
					"in": "query",
					"description": "Keyword search for item",
					"required": false,
					"type": "string"
				}],
				"responses": {
					"200": {
						"description": "A successful response.",
						"schema": {
							"type": "array",
							"items": {
								"$ref": "#/definitions/item"
							}
						}
					}
				},
				"tags": ["negrodom"]
			},
			"post": {
				"summary": "negrodom item",
				"description": "adds an negrodom item",
				"operationId": "addnegrodom",
				"parameters": [{
					"name": "name",
					"in": "formData",
					"description": "Name of item",
					"required": true,
					"type": "string"
				},
				{
					"name": "description",
					"in": "formData",
					"description": "Description of item",
					"required": true,
					"type": "string"
				}],
				"responses": {
					"200": {
						"description": "A successful response.",
						"schema": {
							"type": "array",
							"items": {
								"$ref": "#/definitions/item"
							}
						}
					}
				},
				"tags": ["negrodom"]
			}
		},
		"/negrodom/{id}/": {
			"get": {
				"summary": "negrodom item",
				"description": "returns a single negrodom item",
				"operationId": "getnegrodomItem",
				"parameters": [{
					"name": "id",
					"in": "path",
					"description": "Unique id for item",
					"required": true,
					"type": "integer"
				}],
				"responses": {
					"200": {
						"description": "A successful response.",
						"schema": {
							"type": "array",
							"items": {
								"$ref": "#/definitions/item"
							}
						}
					}
				},
				"tags": ["negrodom"]
			},
			"put": {
				"summary": "negrodom item",
				"description": "update a single negrodom item",
				"operationId": "updatenegrodomItem",
				"parameters": [{
					"name": "id",
					"in": "path",
					"description": "Unique id for item",
					"required": true,
					"type": "integer"
				},
				{
					"name": "name",
					"in": "formData",
					"description": "Name of item",
					"required": true,
					"type": "string"
				},
				{
					"name": "description",
					"in": "formData",
					"description": "Description of item",
					"required": true,
					"type": "string"
				}],
				"responses": {
					"200": {
						"description": "A successful response.",
						"schema": {
							"type": "array",
							"items": {
								"$ref": "#/definitions/item"
							}
						}
					}
				},
				"tags": ["negrodom"]
			},
			"delete": {
				"summary": "negrodom item",
				"description": "deletes a single negrodom item",
				"operationId": "deletenegrodomItem",
				"parameters": [{
					"name": "id",
					"in": "path",
					"description": "Unique id for item",
					"required": true,
					"type": "integer"
				}],
				"responses": {
					"200": {
						"description": "A successful response.",
						"schema": {
							"type": "array",
							"items": {
								"$ref": "#/definitions/item"
							}
						}
					}
				},
				"tags": ["negrodom"]
			}
		}
	},
	"definitions": {
		"item": {
			"properties": {
				"name": {
					"description": "The name of this item.",
					"type": "string"
				},
				"description": {
					"description": "The description of this item.",
					"type": "string"
				}
			}
		}
	}
}